rise/__init__.py
rise/static/README.md
rise/static/main.css
rise/static/main.js
rise/static/rise.png
rise/static/rise.yaml
rise/static/reveal.js/.travis.yml
rise/static/reveal.js/CONTRIBUTING.md
rise/static/reveal.js/LICENSE
rise/static/reveal.js/README.md
rise/static/reveal.js/bower.json
rise/static/reveal.js/demo.html
rise/static/reveal.js/gruntfile.js
rise/static/reveal.js/index.html
rise/static/reveal.js/package.json
rise/static/reveal.js/css/reset.css
rise/static/reveal.js/css/reveal.css
rise/static/reveal.js/css/reveal.css.upstream
rise/static/reveal.js/css/reveal.scss
rise/static/reveal.js/css/print/paper.css
rise/static/reveal.js/css/print/pdf.css
rise/static/reveal.js/css/theme/README.md
rise/static/reveal.js/css/theme/beige.css
rise/static/reveal.js/css/theme/beige.css.patched
rise/static/reveal.js/css/theme/black.css
rise/static/reveal.js/css/theme/black.css.patched
rise/static/reveal.js/css/theme/blood.css
rise/static/reveal.js/css/theme/blood.css.patched
rise/static/reveal.js/css/theme/league.css
rise/static/reveal.js/css/theme/league.css.patched
rise/static/reveal.js/css/theme/moon.css
rise/static/reveal.js/css/theme/moon.css.patched
rise/static/reveal.js/css/theme/night.css
rise/static/reveal.js/css/theme/night.css.patched
rise/static/reveal.js/css/theme/serif.css
rise/static/reveal.js/css/theme/serif.css.patched
rise/static/reveal.js/css/theme/simple.css
rise/static/reveal.js/css/theme/simple.css.patched
rise/static/reveal.js/css/theme/sky.css
rise/static/reveal.js/css/theme/sky.css.patched
rise/static/reveal.js/css/theme/solarized.css
rise/static/reveal.js/css/theme/solarized.css.patched
rise/static/reveal.js/css/theme/white.css
rise/static/reveal.js/css/theme/white.css.patched
rise/static/reveal.js/css/theme/source/beige.scss
rise/static/reveal.js/css/theme/source/black.scss
rise/static/reveal.js/css/theme/source/blood.scss
rise/static/reveal.js/css/theme/source/league.scss
rise/static/reveal.js/css/theme/source/moon.scss
rise-5.7.1.dist-info/LICENSE.md
rise-5.7.1.dist-info/METADATA
rise-5.7.1.dist-info/WHEEL
rise-5.7.1.dist-info/top_level.txt
rise-5.7.1.dist-info/RECORD
